[
    {
        "url": "/quotes/lauren_bowles_570202?src=t_decadent",
        "quote": "I love to bake! I have a huge sweet tooth, and I love to make things like zucchini muffins, you know, anything decadent like that. And I stand by the claim that chocolate can be good for you! I love having a good piece of dark chocolate, one that's 70 percent or more cacao.",
        "author": {
            "name": "Lauren Bowles",
            "url": "/authors/lauren_bowles"
        },
        "topics": [
            {
                "name": "Love",
                "url": "/topics/love"
            },
            {
                "name": "Good",
                "url": "/topics/good"
            },
            {
                "name": "Sweet Tooth",
                "url": "/topics/sweet_tooth"
            }
        ]
    },
    {
        "url": "/quotes/renee_zellweger_169538?src=t_decadent",
        "quote": "Once you've reached the point where you can pay rent, you can go to the vet and you can go to the grocery store, after that point it's all the same. I don't have the appetite for a decadent lifestyle.",
        "author": {
            "name": "Renee Zellweger",
            "url": "/authors/renee_zellweger"
        },
        "topics": [
            {
                "name": "Go",
                "url": "/topics/go"
            },
            {
                "name": "Pay",
                "url": "/topics/pay"
            },
            {
                "name": "Vet",
                "url": "/topics/vet"
            }
        ]
    },
    {
        "url": "/quotes/alice_smith_630787?src=t_decadent",
        "quote": "I like to focus on making the music sound simple and true, and very lush and full. I think music should take you to somewhere else where you have the space to contemplate or exercise your imagination. All the while you should be feeling real good, like when you have a delicious and decadent meal, macaroni and cheese or foie gras.",
        "author": {
            "name": "Alice Smith",
            "url": "/authors/alice_smith"
        },
        "topics": [
            {
                "name": "Sound",
                "url": "/topics/sound"
            },
            {
                "name": "I Think",
                "url": "/topics/i_think"
            },
            {
                "name": "Very",
                "url": "/topics/very"
            }
        ]
    },
    {
        "url": "/quotes/marley_shelton_539810?src=t_decadent",
        "quote": "There's something fabulously decadent about staying in a hotel across the street from where you live.",
        "author": {
            "name": "Marley Shelton",
            "url": "/authors/marley_shelton"
        },
        "topics": [
            {
                "name": "Something",
                "url": "/topics/something"
            },
            {
                "name": "About",
                "url": "/topics/about"
            },
            {
                "name": "Staying",
                "url": "/topics/staying"
            }
        ]
    },
    {
        "url": "/quotes/lee_harvey_oswald_581537?src=t_decadent",
        "quote": "I am a communist and a worker, and I have lived in a decadent capitalist society where the workers are slaves.",
        "author": {
            "name": "Lee Harvey Oswald",
            "url": "/authors/lee_harvey_oswald"
        },
        "topics": [
            {
                "name": "Communist",
                "url": "/topics/communist"
            },
            {
                "name": "Capitalist",
                "url": "/topics/capitalist"
            }
        ]
    },
    {
        "url": "/quotes/gore_vidal_164083?src=t_decadent",
        "quote": "As societies grow decadent, the language grows decadent, too. Words are used to disguise, not to illuminate, action: you liberate a city by destroying it. Words are to confuse, so that at election time people will solemnly vote against their own interests.",
        "author": {
            "name": "Gore Vidal",
            "url": "/authors/gore_vidal"
        },
        "topics": [
            {
                "name": "City",
                "url": "/topics/city"
            },
            {
                "name": "Against",
                "url": "/topics/against"
            },
            {
                "name": "Own",
                "url": "/topics/own"
            }
        ]
    },
    {
        "url": "/quotes/sophie_mcshera_695104?src=t_decadent",
        "quote": "If me and my friends are feeling decadent, we go for afternoon tea.",
        "author": {
            "name": "Sophie McShera",
            "url": "/authors/sophie_mcshera"
        },
        "topics": [
            {
                "name": "Tea",
                "url": "/topics/tea"
            },
            {
                "name": "Me",
                "url": "/topics/me"
            },
            {
                "name": "Afternoon",
                "url": "/topics/afternoon"
            }
        ]
    },
    {
        "url": "/quotes/john_maynard_keynes_152042?src=t_decadent",
        "quote": "The decadent international but individualistic capitalism in the hands of which we found ourselves after the war is not a success. It is not intelligent. It is not beautiful. It is not just. It is not virtuous. And it doesn't deliver the goods.",
        "author": {
            "name": "John Maynard Keynes",
            "url": "/authors/john_maynard_keynes"
        },
        "topics": [
            {
                "name": "Which",
                "url": "/topics/which"
            },
            {
                "name": "Individualistic",
                "url": "/topics/individualistic"
            }
        ]
    },
    {
        "url": "/quotes/h_rap_brown_590236?src=t_decadent",
        "quote": "Revolution comes when human beings set out to correct decadent institutions.",
        "author": {
            "name": "H. Rap Brown",
            "url": "/authors/h_rap_brown"
        },
        "topics": [
            {
                "name": "Correct",
                "url": "/topics/correct"
            },
            {
                "name": "Institutions",
                "url": "/topics/institutions"
            },
            {
                "name": "Set",
                "url": "/topics/set"
            }
        ]
    },
    {
        "url": "/quotes/robert_mapplethorpe_312699?src=t_decadent",
        "quote": "I became the toast of London. A lot of people I met came from these really decadent families where the married men were gay and no one thought anything about it.",
        "author": {
            "name": "Robert Mapplethorpe",
            "url": "/authors/robert_mapplethorpe"
        },
        "topics": [
            {
                "name": "London",
                "url": "/topics/london"
            },
            {
                "name": "Married Men",
                "url": "/topics/married_men"
            },
            {
                "name": "Became",
                "url": "/topics/became"
            }
        ]
    },
    {
        "url": "/quotes/zhang_zhidong_778496?src=t_decadent",
        "quote": "Just now, Christianity is in the ascendant. Buddhism and Taoism are decadent; their influence cannot long hold its own. Buddhism has long since passed its meridian; Taoism has only demons, not gods.",
        "author": {
            "name": "Zhang Zhidong",
            "url": "/authors/zhang_zhidong"
        },
        "topics": [
            {
                "name": "Own",
                "url": "/topics/own"
            },
            {
                "name": "Christianity",
                "url": "/topics/christianity"
            },
            {
                "name": "Gods",
                "url": "/topics/gods"
            }
        ]
    },
    {
        "url": "/quotes/layne_staley_302552?src=t_decadent",
        "quote": "Los Angeles, I don't like that town. Too decadent, and it's slimy.",
        "author": {
            "name": "Layne Staley",
            "url": "/authors/layne_staley"
        },
        "topics": [
            {
                "name": "Town",
                "url": "/topics/town"
            },
            {
                "name": "Los",
                "url": "/topics/los"
            },
            {
                "name": "Angeles",
                "url": "/topics/angeles"
            }
        ]
    },
    {
        "url": "/quotes/marianne_faithfull_575699?src=t_decadent",
        "quote": "I haven't got purity, and I don't think I ever did. I have always been, even as a child, a very decadent little person.",
        "author": {
            "name": "Marianne Faithfull",
            "url": "/authors/marianne_faithfull"
        },
        "topics": [
            {
                "name": "Think",
                "url": "/topics/think"
            },
            {
                "name": "Always",
                "url": "/topics/always"
            },
            {
                "name": "Very",
                "url": "/topics/very"
            }
        ]
    },
    {
        "url": "/quotes/ellen_willis_666380?src=t_decadent",
        "quote": "I can't keep myself from playing roles. The emotionless decadent, looking for diversion from boredom, is a favorite.",
        "author": {
            "name": "Ellen Willis",
            "url": "/authors/ellen_willis"
        },
        "topics": [
            {
                "name": "Myself",
                "url": "/topics/myself"
            },
            {
                "name": "Boredom",
                "url": "/topics/boredom"
            },
            {
                "name": "Roles",
                "url": "/topics/roles"
            }
        ]
    },
    {
        "url": "/quotes/christian_louboutin_566966?src=t_decadent",
        "quote": "To me, the word 'decadent' is so difficult to use; it's a very sensitive word, in a way.",
        "author": {
            "name": "Christian Louboutin",
            "url": "/authors/christian_louboutin"
        },
        "topics": [
            {
                "name": "Me",
                "url": "/topics/me"
            },
            {
                "name": "Use",
                "url": "/topics/use"
            },
            {
                "name": "Very",
                "url": "/topics/very"
            }
        ]
    },
    {
        "url": "/quotes/jill_scott_560943?src=t_decadent",
        "quote": "When I got my success, I became decadent for a while. This was 2003 to 2008. I fell for tiramisu really hard. I've become more moderate since, because African-Americans are prone to diabetes.",
        "author": {
            "name": "Jill Scott",
            "url": "/authors/jill_scott"
        },
        "topics": [
            {
                "name": "Got",
                "url": "/topics/got"
            },
            {
                "name": "Became",
                "url": "/topics/became"
            },
            {
                "name": "While",
                "url": "/topics/while"
            }
        ]
    },
    {
        "url": "/quotes/ivanka_trump_764236?src=t_decadent",
        "quote": "My diet has definitely become greener; however, I am a big proponent of everything in moderation. I enjoy having a farm-to-table dinner, as well as indulging in a special, decadent treat on occasion.",
        "author": {
            "name": "Ivanka Trump",
            "url": "/authors/ivanka_trump"
        },
        "topics": [
            {
                "name": "Big",
                "url": "/topics/big"
            },
            {
                "name": "Occasion",
                "url": "/topics/occasion"
            },
            {
                "name": "However",
                "url": "/topics/however"
            }
        ]
    },
    {
        "url": "/quotes/madonna_ciccone_461124?src=t_decadent",
        "quote": "I don't go to the sale rack. But I wouldn't say I am decadent in my spending. I am careful.",
        "author": {
            "name": "Madonna Ciccone",
            "url": "/authors/madonna_ciccone"
        },
        "topics": [
            {
                "name": "Sale",
                "url": "/topics/sale"
            },
            {
                "name": "Spending",
                "url": "/topics/spending"
            },
            {
                "name": "Rack",
                "url": "/topics/rack"
            }
        ]
    },
    {
        "url": "/quotes/peter_thiel_700201?src=t_decadent",
        "quote": "The millennial generation in the US is the first that has reduced expectations from those of their parents. And I think there is something decadent and declinist about that.",
        "author": {
            "name": "Peter Thiel",
            "url": "/authors/peter_thiel"
        },
        "topics": [
            {
                "name": "Generation",
                "url": "/topics/generation"
            },
            {
                "name": "Think",
                "url": "/topics/think"
            },
            {
                "name": "I Think",
                "url": "/topics/i_think"
            }
        ]
    },
    {
        "url": "/quotes/stephen_kinzer_652261?src=t_decadent",
        "quote": "Sultan Beyazid considered his father's art collection decadent and ordered it sold at auction.",
        "author": {
            "name": "Stephen Kinzer",
            "url": "/authors/stephen_kinzer"
        },
        "topics": [
            {
                "name": "Art",
                "url": "/topics/art"
            },
            {
                "name": "Sold",
                "url": "/topics/sold"
            },
            {
                "name": "Ordered",
                "url": "/topics/ordered"
            }
        ]
    },
    {
        "url": "/quotes/anne_hathaway_443640?src=t_decadent",
        "quote": "I was raised in a solidly upper-middle class family who had really strong values and excess was not one of the things that my family put up with. And there's something wildy decadent about the young-star lifestyle, and I just don't really see the point.",
        "author": {
            "name": "Anne Hathaway",
            "url": "/authors/anne_hathaway"
        },
        "topics": [
            {
                "name": "Strong",
                "url": "/topics/strong"
            },
            {
                "name": "One Of The Things",
                "url": "/topics/one_of_the_things"
            }
        ]
    },
    {
        "url": "/quotes/pat_buchanan_819102?src=t_decadent",
        "quote": "If the Islamic world is so suffused with rage and hatred of us - for our wars, occupations, drone attacks, support of Israel, decadent culture, and tolerance of insults to Islam and the Prophet - why should we call for free elections, when the people will use those elections to vote into power rulers hostile to the United States?",
        "author": {
            "name": "Pat Buchanan",
            "url": "/authors/pat_buchanan"
        },
        "topics": [
            {
                "name": "Use",
                "url": "/topics/use"
            },
            {
                "name": "United",
                "url": "/topics/united"
            },
            {
                "name": "Islamic",
                "url": "/topics/islamic"
            }
        ]
    },
    {
        "url": "/quotes/jay_parini_743216?src=t_decadent",
        "quote": "Fundamentalism takes different forms in different religions, but there is one striking similarity in all forms of fundamentalist thought. Each wishes dearly to hold in check all varieties of 'modern' or 'decadent' thinking.",
        "author": {
            "name": "Jay Parini",
            "url": "/authors/jay_parini"
        },
        "topics": [
            {
                "name": "Thought",
                "url": "/topics/thought"
            },
            {
                "name": "Fundamentalist",
                "url": "/topics/fundamentalist"
            }
        ]
    },
    {
        "url": "/quotes/iman_742235?src=t_decadent",
        "quote": "On my 50th birthday in 2005, my discount-wielding AARP card came in the mail. I hurled it in the trash, put on something fabulous, and had a decadent meal. Just the thought of putting it in my wallet felt like a concession.",
        "author": {
            "name": "Iman",
            "url": "/authors/iman"
        },
        "topics": [
            {
                "name": "Birthday",
                "url": "/topics/birthday"
            },
            {
                "name": "Thought",
                "url": "/topics/thought"
            },
            {
                "name": "Mail",
                "url": "/topics/mail"
            }
        ]
    },
    {
        "url": "/quotes/jenny_packham_898325?src=t_decadent",
        "quote": "From the 1920s through to the 1970s, bridal was related to the fashion of the times. Then in the 1980s, it became more historical, decadent, and ornate.",
        "author": {
            "name": "Jenny Packham",
            "url": "/authors/jenny_packham"
        },
        "topics": [
            {
                "name": "Through",
                "url": "/topics/through"
            },
            {
                "name": "1920s",
                "url": "/topics/1920s"
            },
            {
                "name": "Became",
                "url": "/topics/became"
            }
        ]
    },
    {
        "url": "/quotes/erin_oconnor_605487?src=t_decadent",
        "quote": "I would say I live half in New York and half in Claridge's. How decadent! How hysterical!",
        "author": {
            "name": "Erin O'Connor",
            "url": "/authors/erin_oconnor"
        },
        "topics": [
            {
                "name": "New",
                "url": "/topics/new"
            },
            {
                "name": "How",
                "url": "/topics/how"
            },
            {
                "name": "Half",
                "url": "/topics/half"
            }
        ]
    },
    {
        "url": "/quotes/david_lachapelle_536183?src=t_decadent",
        "quote": "We use fashion for status and to beautify and there's nothing wrong with that, but when it becomes completely unbalanced, then you're living a decadent life. And when that happens on a global scale, you're living in a decadent world.",
        "author": {
            "name": "David LaChapelle",
            "url": "/authors/david_lachapelle"
        },
        "topics": [
            {
                "name": "Living",
                "url": "/topics/living"
            },
            {
                "name": "Nothing",
                "url": "/topics/nothing"
            },
            {
                "name": "Use",
                "url": "/topics/use"
            }
        ]
    },
    {
        "url": "/quotes/seanan_mcguire_618215?src=t_decadent",
        "quote": "I grew up in an apartment that would have made a trailer look really decadent and nice. Pretty much the only dependable thing I had was books.",
        "author": {
            "name": "Seanan McGuire",
            "url": "/authors/seanan_mcguire"
        },
        "topics": [
            {
                "name": "Pretty",
                "url": "/topics/pretty"
            },
            {
                "name": "Made",
                "url": "/topics/made"
            },
            {
                "name": "Dependable",
                "url": "/topics/dependable"
            }
        ]
    },
    {
        "url": "/quotes/chenning_yang_326094?src=t_decadent",
        "quote": "In the final analysis, the incident is seen as originating from an emotional expression of the frustration and anger of the proud people of China who had been subject to ever increasing oppression from without and decadent corruption from within.",
        "author": {
            "name": "Chen-Ning Yang",
            "url": "/authors/chenning_yang"
        },
        "topics": [
            {
                "name": "Proud",
                "url": "/topics/proud"
            },
            {
                "name": "Expression",
                "url": "/topics/expression"
            },
            {
                "name": "Been",
                "url": "/topics/been"
            }
        ]
    },
    {
        "url": "/quotes/virginia_henley_691785?src=t_decadent",
        "quote": "'The Irish Duke' is a sequel to 'The Decadent Duke' about Lady Georgina Gordon who married the Duke of Bedford. 'The Irish Duke' tells the story of their daughter, Lady Louisa, who married James Hamilton, the powerful and wealthy Duke of Abercorn.",
        "author": {
            "name": "Virginia Henley",
            "url": "/authors/virginia_henley"
        },
        "topics": [
            {
                "name": "Wealthy",
                "url": "/topics/wealthy"
            },
            {
                "name": "James",
                "url": "/topics/james"
            },
            {
                "name": "Duke",
                "url": "/topics/duke"
            }
        ]
    },
    {
        "url": "/quotes/dean_jones_756552?src=t_decadent",
        "quote": "If you want a job, do what I did: work for other people for 50 years; but the odds of you getting swallowed up by the blasphemous godless, decadent, deadly spirit of today's show business are thousands to one.",
        "author": {
            "name": "Dean Jones",
            "url": "/authors/dean_jones"
        },
        "topics": [
            {
                "name": "Years",
                "url": "/topics/years"
            },
            {
                "name": "Show",
                "url": "/topics/show"
            },
            {
                "name": "Other",
                "url": "/topics/other"
            }
        ]
    }
]