[
    {
        "url": "/quotes/ajay_mehta_749584",
        "quote": "I used to do a lot of plays in English, Hindi, and Urdu. I wanted to be an actor since I was three and a half.",
        "author": {
            "name": "Ajay Mehta",
            "url": "/quotes/ajay_mehta_749584"
        },
        "topics": [
            {
                "name": "Actor",
                "url": "/topics/actor"
            },
            {
                "name": "Lot",
                "url": "/topics/lot"
            },
            {
                "name": "Plays",
                "url": "/topics/plays"
            }
        ]
    },
    {
        "url": "/quotes/ajay_mehta_749582",
        "quote": "I've always had strong ties with Delhi, and I do stay in touch with my friends and periodically visit the capital. I started my schooling at St. Columbus High School before I went to Mayo College. Delhi, for me, is a historical city with all its beautiful monuments.",
        "author": {
            "name": "Ajay Mehta",
            "url": "/quotes/ajay_mehta_749582"
        },
        "topics": [
            {
                "name": "Strong",
                "url": "/topics/strong"
            },
            {
                "name": "College",
                "url": "/topics/college"
            },
            {
                "name": "Capital",
                "url": "/topics/capital"
            }
        ]
    },
    {
        "url": "/quotes/ajay_mehta_749583",
        "quote": "Mayo College, where I got my grounding, is a private boarding school. It is a traditional school with brilliant teachers including some from overseas.",
        "author": {
            "name": "Ajay Mehta",
            "url": "/quotes/ajay_mehta_749583"
        },
        "topics": [
            {
                "name": "College",
                "url": "/topics/college"
            },
            {
                "name": "Some",
                "url": "/topics/some"
            },
            {
                "name": "Private",
                "url": "/topics/private"
            }
        ]
    },
    {
        "url": "/quotes/ajay_mehta_749585",
        "quote": "I feel respect is in your hands as an actor when portraying a character, particularly when it's from the Indian subcontinent. I do make a conscious effort to do so and often talk to the directors especially about the heavy accent when it's not needed.",
        "author": {
            "name": "Ajay Mehta",
            "url": "/quotes/ajay_mehta_749585"
        },
        "topics": [
            {
                "name": "Hands",
                "url": "/topics/hands"
            },
            {
                "name": "Needed",
                "url": "/topics/needed"
            },
            {
                "name": "Portraying",
                "url": "/topics/portraying"
            }
        ]
    },
    {
        "url": "/quotes/ajay_mehta_749586",
        "quote": "My father was a very special human being. He was brilliant in academics, sports and the arts. He wrote, performed and directed plays in English and Hindi/Urdu at his regiment.",
        "author": {
            "name": "Ajay Mehta",
            "url": "/quotes/ajay_mehta_749586"
        },
        "topics": [
            {
                "name": "Human Being",
                "url": "/topics/human_being"
            },
            {
                "name": "Brilliant",
                "url": "/topics/brilliant"
            },
            {
                "name": "Very",
                "url": "/topics/very"
            }
        ]
    },
    {
        "url": "/quotes/ajay_mehta_749587",
        "quote": "My father lived life to the fullest, even though it was cut short at a young age in 1962. He was known for his intelligence, wit, wisdom, a wonderful sense of humour, a great personality, and a genuine goodwill towards all.",
        "author": {
            "name": "Ajay Mehta",
            "url": "/quotes/ajay_mehta_749587"
        },
        "topics": [
            {
                "name": "Young",
                "url": "/topics/young"
            },
            {
                "name": "Cut",
                "url": "/topics/cut"
            },
            {
                "name": "Goodwill",
                "url": "/topics/goodwill"
            }
        ]
    },
    {
        "url": "/quotes/ajay_mehta_749588",
        "quote": "My mother enjoyed acting as well with my father, who used to direct her in plays at his regiment. My sister is an excellent singer. However, it was only me who decided to pursue acting as a career.",
        "author": {
            "name": "Ajay Mehta",
            "url": "/quotes/ajay_mehta_749588"
        },
        "topics": [
            {
                "name": "Career",
                "url": "/topics/career"
            },
            {
                "name": "However",
                "url": "/topics/however"
            },
            {
                "name": "Plays",
                "url": "/topics/plays"
            }
        ]
    },
    {
        "url": "/quotes/ajay_mehta_749589",
        "quote": "Losing my father at a tender age was hard, and I felt it more so while growing up when I needed a father to talk to. Especially while pursuing an acting career where I would have loved his guidance and advice, since it was his passion as well.",
        "author": {
            "name": "Ajay Mehta",
            "url": "/quotes/ajay_mehta_749589"
        },
        "topics": [
            {
                "name": "Career",
                "url": "/topics/career"
            },
            {
                "name": "Needed",
                "url": "/topics/needed"
            },
            {
                "name": "Pursuing",
                "url": "/topics/pursuing"
            }
        ]
    }
]