[
    {
        "url": "/quotes/douglas_trumbull_896550",
        "quote": "'2001' used a lot of what's called 'front projection.' You project an image onto this giant reflective screen, and the image bounces back and comes back to the lens and seems to be in the background behind the actors. The whole 'dawn of man' sequence in '2001' was projected eight-by-ten photographs of the African savannah.",
        "author": {
            "name": "Douglas Trumbull",
            "url": "/quotes/douglas_trumbull_896550"
        },
        "topics": [
            {
                "name": "Project",
                "url": "/topics/project"
            },
            {
                "name": "Behind",
                "url": "/topics/behind"
            },
            {
                "name": "Screen",
                "url": "/topics/screen"
            }
        ]
    },
    {
        "url": "/quotes/douglas_trumbull_896551",
        "quote": "If you want people to come to theaters, you better do something different.",
        "author": {
            "name": "Douglas Trumbull",
            "url": "/quotes/douglas_trumbull_896551"
        },
        "topics": [
            {
                "name": "Better",
                "url": "/topics/better"
            },
            {
                "name": "Want",
                "url": "/topics/want"
            },
            {
                "name": "Theaters",
                "url": "/topics/theaters"
            }
        ]
    },
    {
        "url": "/quotes/douglas_trumbull_896552",
        "quote": "I got hooked on immersive cinema when I worked on '2001,' which was initially shown on these Cinerama screens, which were all 90 feet wide and deeply curved.",
        "author": {
            "name": "Douglas Trumbull",
            "url": "/quotes/douglas_trumbull_896552"
        },
        "topics": [
            {
                "name": "Feet",
                "url": "/topics/feet"
            },
            {
                "name": "Which",
                "url": "/topics/which"
            },
            {
                "name": "Wide",
                "url": "/topics/wide"
            }
        ]
    },
    {
        "url": "/quotes/douglas_trumbull_896553",
        "quote": "I'd formed a research and development company under the banner of Paramount Pictures back in about 1975, and its mandate was to explore advanced forms of entertainment, not just movies.",
        "author": {
            "name": "Douglas Trumbull",
            "url": "/quotes/douglas_trumbull_896553"
        },
        "topics": [
            {
                "name": "Development",
                "url": "/topics/development"
            },
            {
                "name": "Mandate",
                "url": "/topics/mandate"
            }
        ]
    },
    {
        "url": "/quotes/douglas_trumbull_896554",
        "quote": "I wouldn't apply high frame rates to a love story or a thriller or a film noir or a mystery.",
        "author": {
            "name": "Douglas Trumbull",
            "url": "/quotes/douglas_trumbull_896554"
        },
        "topics": [
            {
                "name": "Love",
                "url": "/topics/love"
            },
            {
                "name": "Apply",
                "url": "/topics/apply"
            },
            {
                "name": "Rates",
                "url": "/topics/rates"
            }
        ]
    },
    {
        "url": "/quotes/douglas_trumbull_896555",
        "quote": "The diversity of content is now offered from streaming and downloading, so young people are really not going to theaters because they don't see any particular benefit.",
        "author": {
            "name": "Douglas Trumbull",
            "url": "/quotes/douglas_trumbull_896555"
        },
        "topics": [
            {
                "name": "Young",
                "url": "/topics/young"
            },
            {
                "name": "Going",
                "url": "/topics/going"
            },
            {
                "name": "Particular",
                "url": "/topics/particular"
            }
        ]
    },
    {
        "url": "/quotes/douglas_trumbull_896556",
        "quote": "There's been a bit of confusion about Showscan. The basic problem was, it was film and it was 70 mm and it was a lot of it, so the negative cost was very high, the print costs were very high, and it also required conversion of the projectors and theaters and a lot of costs. I just couldn't get any traction in the theatrical movie industry to do it.",
        "author": {
            "name": "Douglas Trumbull",
            "url": "/quotes/douglas_trumbull_896556"
        },
        "topics": [
            {
                "name": "Very",
                "url": "/topics/very"
            },
            {
                "name": "Been",
                "url": "/topics/been"
            },
            {
                "name": "Theatrical",
                "url": "/topics/theatrical"
            }
        ]
    },
    {
        "url": "/quotes/douglas_trumbull_896557",
        "quote": "Peter Jackson is a real big hero of mine because he had the nerve to make 'The Hobbit' at 48 frames per second.",
        "author": {
            "name": "Douglas Trumbull",
            "url": "/quotes/douglas_trumbull_896557"
        },
        "topics": [
            {
                "name": "Big",
                "url": "/topics/big"
            },
            {
                "name": "Mine",
                "url": "/topics/mine"
            },
            {
                "name": "Frames",
                "url": "/topics/frames"
            }
        ]
    },
    {
        "url": "/quotes/douglas_trumbull_896558",
        "quote": "I think 'Avatar' is much more appropriate to high frame rates because it's like a ride, and it's futuristic, and vividness and sharp edges and clarity would be an asset.",
        "author": {
            "name": "Douglas Trumbull",
            "url": "/quotes/douglas_trumbull_896558"
        },
        "topics": [
            {
                "name": "Think",
                "url": "/topics/think"
            },
            {
                "name": "I Think",
                "url": "/topics/i_think"
            },
            {
                "name": "Appropriate",
                "url": "/topics/appropriate"
            }
        ]
    },
    {
        "url": "/quotes/douglas_trumbull_896559",
        "quote": "My personal feeling is that ultra-high frame rates and ultra-vivid giant screen movies can be like a window onto reality. And if you recognize it as such, you can write your screenplay, direct your movie, edit it, and present it as a live experience - not like a movie.",
        "author": {
            "name": "Douglas Trumbull",
            "url": "/quotes/douglas_trumbull_896559"
        },
        "topics": [
            {
                "name": "Screen",
                "url": "/topics/screen"
            },
            {
                "name": "Movie",
                "url": "/topics/movie"
            },
            {
                "name": "Direct",
                "url": "/topics/direct"
            }
        ]
    },
    {
        "url": "/quotes/douglas_trumbull_896560",
        "quote": "I have the deepest respect for Terrence Malick and greatly enjoyed helping him on 'Tree of Life.' I consider him to be a good personal friend and professional contemporary.",
        "author": {
            "name": "Douglas Trumbull",
            "url": "/quotes/douglas_trumbull_896560"
        },
        "topics": [
            {
                "name": "Tree",
                "url": "/topics/tree"
            },
            {
                "name": "Personal",
                "url": "/topics/personal"
            },
            {
                "name": "Helping",
                "url": "/topics/helping"
            }
        ]
    },
    {
        "url": "/quotes/douglas_trumbull_896561",
        "quote": "Working on '2001' was my film school. Stanley Kubrick was my mentor.",
        "author": {
            "name": "Douglas Trumbull",
            "url": "/quotes/douglas_trumbull_896561"
        },
        "topics": [
            {
                "name": "School",
                "url": "/topics/school"
            },
            {
                "name": "Mentor",
                "url": "/topics/mentor"
            },
            {
                "name": "Film School",
                "url": "/topics/film_school"
            }
        ]
    },
    {
        "url": "/quotes/douglas_trumbull_896541",
        "quote": "There was every reason to honestly say that 3D was a gimmick. And it's largely true. And it's largely pretty bad. When you put a filter in front of the projector, and you put on your glasses and cut the light in half again, the movies are dim as hell, and they give you headaches and eye strain, and it's terrible.",
        "author": {
            "name": "Douglas Trumbull",
            "url": "/quotes/douglas_trumbull_896541"
        },
        "topics": [
            {
                "name": "Cut",
                "url": "/topics/cut"
            },
            {
                "name": "Half",
                "url": "/topics/half"
            },
            {
                "name": "Reason",
                "url": "/topics/reason"
            }
        ]
    },
    {
        "url": "/quotes/douglas_trumbull_253741",
        "quote": "My particular aesthetic of light and color and design wouldn't change as a result of working with computer graphics rather than with slit scan or miniatures.",
        "author": {
            "name": "Douglas Trumbull",
            "url": "/quotes/douglas_trumbull_253741"
        },
        "topics": [
            {
                "name": "Color",
                "url": "/topics/color"
            },
            {
                "name": "Aesthetic",
                "url": "/topics/aesthetic"
            },
            {
                "name": "Rather",
                "url": "/topics/rather"
            }
        ]
    },
    {
        "url": "/quotes/douglas_trumbull_253736",
        "quote": "IBM was the original contractor for much of the computer interface design on the film.",
        "author": {
            "name": "Douglas Trumbull",
            "url": "/quotes/douglas_trumbull_253736"
        },
        "topics": [
            {
                "name": "Computer",
                "url": "/topics/computer"
            },
            {
                "name": "Contractor",
                "url": "/topics/contractor"
            },
            {
                "name": "IBM",
                "url": "/topics/ibm"
            }
        ]
    },
    {
        "url": "/quotes/douglas_trumbull_253747",
        "quote": "There were IBM logos designed for the film, and there were IBM design consultants working with Kubrick on the layout of the controls and computer screens.",
        "author": {
            "name": "Douglas Trumbull",
            "url": "/quotes/douglas_trumbull_253747"
        },
        "topics": [
            {
                "name": "Film",
                "url": "/topics/film"
            },
            {
                "name": "Controls",
                "url": "/topics/controls"
            },
            {
                "name": "Kubrick",
                "url": "/topics/kubrick"
            }
        ]
    },
    {
        "url": "/quotes/douglas_trumbull_253748",
        "quote": "There's a consistency in my work that pops up independent of the limitations of the technology.",
        "author": {
            "name": "Douglas Trumbull",
            "url": "/quotes/douglas_trumbull_253748"
        },
        "topics": [
            {
                "name": "Work",
                "url": "/topics/work"
            },
            {
                "name": "Independent",
                "url": "/topics/independent"
            },
            {
                "name": "Pops",
                "url": "/topics/pops"
            }
        ]
    },
    {
        "url": "/quotes/douglas_trumbull_253733",
        "quote": "I honestly believe that the next big leap in immersive technology will be very much like Brainstorm.",
        "author": {
            "name": "Douglas Trumbull",
            "url": "/quotes/douglas_trumbull_253733"
        },
        "topics": [
            {
                "name": "Next",
                "url": "/topics/next"
            },
            {
                "name": "Big",
                "url": "/topics/big"
            },
            {
                "name": "Very",
                "url": "/topics/very"
            }
        ]
    },
    {
        "url": "/quotes/douglas_trumbull_253729",
        "quote": "But as far as the concept of HAL, who HAL was, his character - I had no role in creating him.",
        "author": {
            "name": "Douglas Trumbull",
            "url": "/quotes/douglas_trumbull_253729"
        },
        "topics": [
            {
                "name": "Character",
                "url": "/topics/character"
            },
            {
                "name": "His",
                "url": "/topics/his"
            },
            {
                "name": "Hal",
                "url": "/topics/hal"
            }
        ]
    },
    {
        "url": "/quotes/douglas_trumbull_253730",
        "quote": "Clearly, if we'd had the kind of computer graphics capability then that we have now, the Star Gate sequence would be much more complex than flat planes of light and color.",
        "author": {
            "name": "Douglas Trumbull",
            "url": "/quotes/douglas_trumbull_253730"
        },
        "topics": [
            {
                "name": "Color",
                "url": "/topics/color"
            },
            {
                "name": "Star",
                "url": "/topics/star"
            },
            {
                "name": "Kind",
                "url": "/topics/kind"
            }
        ]
    },
    {
        "url": "/quotes/douglas_trumbull_253735",
        "quote": "I visited a scientist who had a helmet with magnetic fields controlled by computer sequences that could profoundly affect your mood and your perceptions.",
        "author": {
            "name": "Douglas Trumbull",
            "url": "/quotes/douglas_trumbull_253735"
        },
        "topics": [
            {
                "name": "Mood",
                "url": "/topics/mood"
            },
            {
                "name": "Scientist",
                "url": "/topics/scientist"
            },
            {
                "name": "Profoundly",
                "url": "/topics/profoundly"
            }
        ]
    },
    {
        "url": "/quotes/douglas_trumbull_253739",
        "quote": "It was the point where things became much more abstract and less literal than in the bulk of the film, which was hardcore rockets and space and planets - all a fairly straightforward evolution from what I had been doing before.",
        "author": {
            "name": "Douglas Trumbull",
            "url": "/quotes/douglas_trumbull_253739"
        },
        "topics": [
            {
                "name": "Straightforward",
                "url": "/topics/straightforward"
            },
            {
                "name": "Became",
                "url": "/topics/became"
            }
        ]
    },
    {
        "url": "/quotes/douglas_trumbull_253740",
        "quote": "My first job on 2001 was to make all of the HAL readouts: the 16 screens that surround HAL's eyes.",
        "author": {
            "name": "Douglas Trumbull",
            "url": "/quotes/douglas_trumbull_253740"
        },
        "topics": [
            {
                "name": "Eyes",
                "url": "/topics/eyes"
            },
            {
                "name": "Hal",
                "url": "/topics/hal"
            },
            {
                "name": "Screens",
                "url": "/topics/screens"
            }
        ]
    },
    {
        "url": "/quotes/douglas_trumbull_253746",
        "quote": "The technology of the time dictated the way things looked.",
        "author": {
            "name": "Douglas Trumbull",
            "url": "/quotes/douglas_trumbull_253746"
        },
        "topics": [
            {
                "name": "Technology",
                "url": "/topics/technology"
            },
            {
                "name": "Things",
                "url": "/topics/things"
            },
            {
                "name": "Looked",
                "url": "/topics/looked"
            }
        ]
    },
    {
        "url": "/quotes/douglas_trumbull_253749",
        "quote": "We're not that far from being able to plant images, memories, and emotional states directly into the brain.",
        "author": {
            "name": "Douglas Trumbull",
            "url": "/quotes/douglas_trumbull_253749"
        },
        "topics": [
            {
                "name": "Emotional",
                "url": "/topics/emotional"
            },
            {
                "name": "Being",
                "url": "/topics/being"
            },
            {
                "name": "Images",
                "url": "/topics/images"
            }
        ]
    },
    {
        "url": "/quotes/douglas_trumbull_253750",
        "quote": "When I worked on 2001 - which was my first feature film - I was deeply and permanently affected by the notion that a movie could be like a first-person experience.",
        "author": {
            "name": "Douglas Trumbull",
            "url": "/quotes/douglas_trumbull_253750"
        },
        "topics": [
            {
                "name": "Which",
                "url": "/topics/which"
            },
            {
                "name": "Movie",
                "url": "/topics/movie"
            },
            {
                "name": "Feature Film",
                "url": "/topics/feature_film"
            }
        ]
    },
    {
        "url": "/quotes/douglas_trumbull_896537",
        "quote": "I meet astrophysicists almost every week who say that they went into their line of work because of '2001.'",
        "author": {
            "name": "Douglas Trumbull",
            "url": "/quotes/douglas_trumbull_896537"
        },
        "topics": [
            {
                "name": "Week",
                "url": "/topics/week"
            },
            {
                "name": "Line",
                "url": "/topics/line"
            },
            {
                "name": "Almost",
                "url": "/topics/almost"
            }
        ]
    },
    {
        "url": "/quotes/douglas_trumbull_896538",
        "quote": "Movies used to be called the 'flicks' because they flickered badly: because 16 or 18 frames a second - which was those hand cranked movies on a single-bladed shutter - was really badly flickering.",
        "author": {
            "name": "Douglas Trumbull",
            "url": "/quotes/douglas_trumbull_896538"
        },
        "topics": [
            {
                "name": "Which",
                "url": "/topics/which"
            },
            {
                "name": "Badly",
                "url": "/topics/badly"
            },
            {
                "name": "Frames",
                "url": "/topics/frames"
            }
        ]
    },
    {
        "url": "/quotes/douglas_trumbull_896539",
        "quote": "I took IMAX public back in the early '90s.",
        "author": {
            "name": "Douglas Trumbull",
            "url": "/quotes/douglas_trumbull_896539"
        },
        "topics": [
            {
                "name": "Back",
                "url": "/topics/back"
            },
            {
                "name": "Public",
                "url": "/topics/public"
            },
            {
                "name": "Took",
                "url": "/topics/took"
            }
        ]
    },
    {
        "url": "/quotes/douglas_trumbull_896540",
        "quote": "It's not appropriate to a love story, or - there are a million stories you could think of that don't need 3D. A lot of movies don't even need color!",
        "author": {
            "name": "Douglas Trumbull",
            "url": "/quotes/douglas_trumbull_896540"
        },
        "topics": [
            {
                "name": "Love",
                "url": "/topics/love"
            },
            {
                "name": "Think",
                "url": "/topics/think"
            },
            {
                "name": "Appropriate",
                "url": "/topics/appropriate"
            }
        ]
    },
    {
        "url": "/quotes/douglas_trumbull_896542",
        "quote": "I'm developing some high-frame-rate 3-D processes that are going to be, I hope, indistiguishable from reality. This will be quite an unusual cinematic event - you don't just tell an ordinary story, it's more of a first-person experience where the melodrama doesn't get in the way. Being inside the movie rather than looking at the movie.",
        "author": {
            "name": "Douglas Trumbull",
            "url": "/quotes/douglas_trumbull_896542"
        },
        "topics": [
            {
                "name": "Some",
                "url": "/topics/some"
            },
            {
                "name": "Rather",
                "url": "/topics/rather"
            },
            {
                "name": "Movie",
                "url": "/topics/movie"
            }
        ]
    },
    {
        "url": "/quotes/douglas_trumbull_896543",
        "quote": "When I was a young man in school, I used to read science fiction and really liked it. And as I became a young artist, I was filling up my portfolio with alien planets and spacecraft and things like that.",
        "author": {
            "name": "Douglas Trumbull",
            "url": "/quotes/douglas_trumbull_896543"
        },
        "topics": [
            {
                "name": "Young",
                "url": "/topics/young"
            },
            {
                "name": "Fiction",
                "url": "/topics/fiction"
            },
            {
                "name": "Became",
                "url": "/topics/became"
            }
        ]
    },
    {
        "url": "/quotes/douglas_trumbull_896544",
        "quote": "I'm fearless when it comes to engineering and motors and gears and pulleys and glass and artwork.",
        "author": {
            "name": "Douglas Trumbull",
            "url": "/quotes/douglas_trumbull_896544"
        },
        "topics": [
            {
                "name": "Fearless",
                "url": "/topics/fearless"
            },
            {
                "name": "Engineering",
                "url": "/topics/engineering"
            },
            {
                "name": "Glass",
                "url": "/topics/glass"
            }
        ]
    },
    {
        "url": "/quotes/douglas_trumbull_896545",
        "quote": "Every movie presents unusual challenges, and I like solving the problems with a combination of artwork and engineering.",
        "author": {
            "name": "Douglas Trumbull",
            "url": "/quotes/douglas_trumbull_896545"
        },
        "topics": [
            {
                "name": "Challenges",
                "url": "/topics/challenges"
            },
            {
                "name": "Movie",
                "url": "/topics/movie"
            },
            {
                "name": "Solving",
                "url": "/topics/solving"
            }
        ]
    },
    {
        "url": "/quotes/douglas_trumbull_896546",
        "quote": "I learned a lot on '2001.'",
        "author": {
            "name": "Douglas Trumbull",
            "url": "/quotes/douglas_trumbull_896546"
        },
        "topics": [
            {
                "name": "Learned",
                "url": "/topics/learned"
            },
            {
                "name": "Lot",
                "url": "/topics/lot"
            }
        ]
    },
    {
        "url": "/quotes/douglas_trumbull_896547",
        "quote": "I'd rather have fewer spectacular theaters than tons of cheap little multiplexes.",
        "author": {
            "name": "Douglas Trumbull",
            "url": "/quotes/douglas_trumbull_896547"
        },
        "topics": [
            {
                "name": "Rather",
                "url": "/topics/rather"
            },
            {
                "name": "Theaters",
                "url": "/topics/theaters"
            },
            {
                "name": "Tons",
                "url": "/topics/tons"
            }
        ]
    },
    {
        "url": "/quotes/douglas_trumbull_896548",
        "quote": "I think miniatures are still superior to a lot of computer graphics.",
        "author": {
            "name": "Douglas Trumbull",
            "url": "/quotes/douglas_trumbull_896548"
        },
        "topics": [
            {
                "name": "Think",
                "url": "/topics/think"
            },
            {
                "name": "Lot",
                "url": "/topics/lot"
            },
            {
                "name": "Still",
                "url": "/topics/still"
            }
        ]
    },
    {
        "url": "/quotes/douglas_trumbull_896549",
        "quote": "I like the unknown. That's what Terry Malick has always really liked. He's always looking for the unexpected.",
        "author": {
            "name": "Douglas Trumbull",
            "url": "/quotes/douglas_trumbull_896549"
        },
        "topics": [
            {
                "name": "Unexpected",
                "url": "/topics/unexpected"
            },
            {
                "name": "Always",
                "url": "/topics/always"
            },
            {
                "name": "Like",
                "url": "/topics/like"
            }
        ]
    }
]